[
  {
    "scenario_id": "crypto_2500",
    "name": "Crypto $2.5K",
    "timestamp": "2026-07-21T02:21:01.145413",
    "starting_capital": 2500,
    "equity_cad": 2484.63,
    "cash_cad": 2484.63,
    "trades": 356,
    "positions": 11,
    "monthly_deposit": 0,
    "risk_profile": "pennies"
  },
  {
    "scenario_id": "fiat_1k",
    "name": "Fiat $1K",
    "timestamp": "2026-07-21T02:21:01.145456",
    "starting_capital": 1000,
    "equity_cad": 797.45,
    "cash_cad": 797.45,
    "trades": 407,
    "positions": 4,
    "monthly_deposit": 0,
    "risk_profile": "pennies"
  },
  {
    "scenario_id": "basic_1k",
    "name": "Basic $1K",
    "timestamp": "2026-07-21T02:21:01.145467",
    "starting_capital": 1000,
    "equity_cad": 1001.55,
    "cash_cad": -0.0,
    "trades": 44,
    "positions": 1,
    "monthly_deposit": 100,
    "risk_profile": "balanced"
  },
  {
    "scenario_id": "growth_2500",
    "name": "Growth $2.5K",
    "timestamp": "2026-07-21T02:21:01.145477",
    "starting_capital": 2500,
    "equity_cad": 2503.87,
    "cash_cad": 0.0,
    "trades": 108,
    "positions": 1,
    "monthly_deposit": 250,
    "risk_profile": "balanced"
  },
  {
    "scenario_id": "pro_5k",
    "name": "Pro $5K",
    "timestamp": "2026-07-21T02:21:01.145486",
    "starting_capital": 5000,
    "equity_cad": 5007.74,
    "cash_cad": -0.0,
    "trades": 216,
    "positions": 1,
    "monthly_deposit": 500,
    "risk_profile": "aggressive"
  }
]