[
  {
    "scenario_id": "crypto_2500",
    "name": "Crypto $2.5K",
    "timestamp": "2026-07-23T18:31:24.242939",
    "starting_capital": 5000.0,
    "equity_cad": 446.08,
    "cash_cad": 446.08,
    "trades": 78,
    "positions": 8,
    "monthly_deposit": 0,
    "risk_profile": "pennies"
  },
  {
    "scenario_id": "fiat_1k",
    "name": "Fiat $1K",
    "timestamp": "2026-07-23T18:31:24.243032",
    "starting_capital": 1000,
    "equity_cad": 996.63,
    "cash_cad": 996.63,
    "trades": 101,
    "positions": 2,
    "monthly_deposit": 0,
    "risk_profile": "pennies"
  },
  {
    "scenario_id": "basic_1k",
    "name": "Basic $1K",
    "timestamp": "2026-07-23T18:31:24.243047",
    "starting_capital": 1000,
    "equity_cad": 991.97,
    "cash_cad": -0.0,
    "trades": 89,
    "positions": 1,
    "monthly_deposit": 100,
    "risk_profile": "balanced"
  },
  {
    "scenario_id": "growth_2500",
    "name": "Growth $2.5K",
    "timestamp": "2026-07-23T18:31:24.243059",
    "starting_capital": 2500,
    "equity_cad": 2489.94,
    "cash_cad": 1354.79,
    "trades": 101,
    "positions": 1,
    "monthly_deposit": 250,
    "risk_profile": "balanced"
  },
  {
    "scenario_id": "pro_5k",
    "name": "Pro $5K",
    "timestamp": "2026-07-23T18:31:24.243071",
    "starting_capital": 5000,
    "equity_cad": 4989.94,
    "cash_cad": 3854.79,
    "trades": 101,
    "positions": 1,
    "monthly_deposit": 500,
    "risk_profile": "aggressive"
  }
]